
[
  {
    "kernelSource": {
      "name": "kernel",
      "repo": "https://github.com/malkist01/teletubies.git",
      "branch": "su",
      "device": "mido",
      "defconfig": "teletubies_defconfig"
  },
    "toolchains": [
      {
        "repo": "https://gitlab.com/Panchajanya1999/azure-clang.git",
        "branch": "main",
        "name": "clang",
        "binPath": ["bin"]
      }
    ],
    "params": {
     "ARCH": "arm64",
      "CC": "clang/bin/clang",
      "externalCommand": {
        "CROSS_COMPILE": "clang/bin/aarch64-linux-gnu-",
        "CROSS_COMPILE_ARM32": "clang/bin/arm-linux-gnueabi-",
        "LD": "clang/bin/ld.lld"
        "AS": "clang/bin/llvm-as"
        "AR": "clang/bin/llvm-ar",
        "NM": "clang/bin/llvm-nm",
        "OBJCOPY": "clang/bin/llvm-objcopy",
        "OBJDUMP": "clang/bin/llvm-objdump",
        "STRIP": "clang/bin/llvm-strip",
      }
    },
    "AnyKernel3": {
      "use": true,
      "release": true,
      "repo": "https://github.com/malkist01/anykernel3.git",
      "branch": "master"
    }
  }
]
